Workbook

Sheet Рассылка
A1: День | B1: Страна | C1: Тип | D1: Фирма | E1: Сайт | F1: Контактное лицо | G1: Канал | H1: Email / форма | I1: Род занятий | J1: Резидентство в практиках | K1: Лицензия / юрстатус | L1: Языки | M1: Письмо | N1: Модель | O1: Тема письма | P1: Тело письма | Q1: Зачем эта фирма | R1: Статус | S1: Дата отправки | T1: Дата повтора | U1: Дата ответа | V1: Что ответили про деньги | W1: Заметки
A2: 1 | B2: Португалия | C2: юрфирма | D2: Defesa Legal / F+AS | E2: defesalegal.pt | F2: Jorge Ferraz | G2: email | H2: geral@defesalegal.pt | I2: бутик: иммиграция, гражданство, недвижимость | J2: да | K2: адвокат подтверждён — cédula 9398P | L2: PT, EN | M2: B | N2: бесплатная — закон | O2: Enquiries about the Portuguese Golden Visa — no fee either way | P2: Hello, My name is Alex Bandziuk. I run moveandinvest.com, an independent comparison of residency-by-investment routes in Portugal, Greece, Malta, the UAE and Cyprus. I am not an agency and I sell none of these programmes. I am writing to ask whether you would take enquiries from readers asking about your jurisdiction. No money passes in either direction, and that is deliberate rather than generous: your professional rules do not permit paying for an introduced client, so I ask for nothing and you would owe nothing. An enquiry is one person who filled in six fields in their own words — the country, a budget ceiling, a timeline, the goal, a free-text paragraph, a name and an email — and gave explicit consent to be passed to a single adviser. One firm per jurisdiction, never resold, never sent to two firms. The form is at moveandinvest.com/for-partners. What I get is that readers who write to me get an answer, which is the only thing that makes the site worth running. If you would rather not, one line saying so is enough and I will not write again. Alex Bandziuk moveandinvest.com · office@moveandinvest.com | Q2: Единственная реестровая проверка, которая сошлась. | R2: не отправлено | T2: =IF(S2="","",S2+14)
A3: 2 | B3: Португалия | C3: юрфирма | D3: LVP Advogados | E3: lvpadvogados.com | F3: Joana Torres Fernandes | G3: email | H3: enquiries@lvpadvogados.com | I3: бутик для иностранных клиентов | J3: да | K3: не проверялся | L3: PT, EN | M3: B | N3: бесплатная — закон | O3: Enquiries about the Portuguese Golden Visa — no fee either way | P3: Hello, My name is Alex Bandziuk. I run moveandinvest.com, an independent comparison of residency-by-investment routes in Portugal, Greece, Malta, the UAE and Cyprus. I am not an agency and I sell none of these programmes. I am writing to ask whether you would take enquiries from readers asking about your jurisdiction. No money passes in either direction, and that is deliberate rather than generous: your professional rules do not permit paying for an introduced client, so I ask for nothing and you would owe nothing. An enquiry is one person who filled in six fields in their own words — the country, a budget ceiling, a timeline, the goal, a free-text paragraph, a name and an email — and gave explicit consent to be passed to a single adviser. One firm per jurisdiction, never resold, never sent to two firms. The form is at moveandinvest.com/for-partners. What I get is that readers who write to me get an answer, which is the only thing that makes the site worth running. If you would rather not, one line saying so is enough and I will not write again. Alex Bandziuk moveandinvest.com · office@moveandinvest.com | Q3: «Clients from more than 150 countries». | R3: не отправлено | T3: =IF(S3="","",S3+14)
A4: 2 | B4: Португалия | C4: юрфирма | D4: SRS Advogados | E4: srslegal.pt | G4: email | H4: srsglobal@srslegal.pt | I4: полносервисная, 100+ юристов | J4: да — Immigration, Golden Visa and Citizenship | K4: cédula 44416E не сходится | L4: PT, EN | M4: B | N4: бесплатная — закон | O4: Enquiries about the Portuguese Golden Visa — no fee either way | P4: Hello, My name is Alex Bandziuk. I run moveandinvest.com, an independent comparison of residency-by-investment routes in Portugal, Greece, Malta, the UAE and Cyprus. I am not an agency and I sell none of these programmes. I am writing to ask whether you would take enquiries from readers asking about your jurisdiction. No money passes in either direction, and that is deliberate rather than generous: your professional rules do not permit paying for an introduced client, so I ask for nothing and you would owe nothing. An enquiry is one person who filled in six fields in their own words — the country, a budget ceiling, a timeline, the goal, a free-text paragraph, a name and an email — and gave explicit consent to be passed to a single adviser. One firm per jurisdiction, never resold, never sent to two firms. The form is at moveandinvest.com/for-partners. What I get is that readers who write to me get an answer, which is the only thing that makes the site worth running. If you would rather not, one line saying so is enough and I will not write again. Alex Bandziuk moveandinvest.com · office@moveandinvest.com | R4: не отправлено | T4: =IF(S4="","",S4+14)
A5: 2 | B5: Португалия | C5: юрфирма | D5: CMS Portugal | E5: cms.law | G5: email | H5: cms@cmsportugal.com | I5: международная полносервисная | J5: да — «Golden Visa since 2012» | K5: не проверялся | L5: PT, EN | M5: B | N5: бесплатная — закон | O5: Enquiries about the Portuguese Golden Visa — no fee either way | P5: Hello, My name is Alex Bandziuk. I run moveandinvest.com, an independent comparison of residency-by-investment routes in Portugal, Greece, Malta, the UAE and Cyprus. I am not an agency and I sell none of these programmes. I am writing to ask whether you would take enquiries from readers asking about your jurisdiction. No money passes in either direction, and that is deliberate rather than generous: your professional rules do not permit paying for an introduced client, so I ask for nothing and you would owe nothing. An enquiry is one person who filled in six fields in their own words — the country, a budget ceiling, a timeline, the goal, a free-text paragraph, a name and an email — and gave explicit consent to be passed to a single adviser. One firm per jurisdiction, never resold, never sent to two firms. The form is at moveandinvest.com/for-partners. What I get is that readers who write to me get an answer, which is the only thing that makes the site worth running. If you would rather not, one line saying so is enough and I will not write again. Alex Bandziuk moveandinvest.com · office@moveandinvest.com | R5: не отправлено | T5: =IF(S5="","",S5+14)
A6: 2 | B6: Португалия | C6: юрфирма | D6: VdA — Vieira de Almeida | E6: vda.pt | G6: email | H6: vieiradealmeida@vda.pt | I6: международная полносервисная, 330+ юристов | J6: НЕТ в практиках | K6: не проверялся | L6: PT, EN | M6: B | N6: бесплатная — закон | O6: Enquiries about the Portuguese Golden Visa — no fee either way | P6: Hello, My name is Alex Bandziuk. I run moveandinvest.com, an independent comparison of residency-by-investment routes in Portugal, Greece, Malta, the UAE and Cyprus. I am not an agency and I sell none of these programmes. I am writing to ask whether you would take enquiries from readers asking about your jurisdiction. No money passes in either direction, and that is deliberate rather than generous: your professional rules do not permit paying for an introduced client, so I ask for nothing and you would owe nothing. An enquiry is one person who filled in six fields in their own words — the country, a budget ceiling, a timeline, the goal, a free-text paragraph, a name and an email — and gave explicit consent to be passed to a single adviser. One firm per jurisdiction, never resold, never sent to two firms. The form is at moveandinvest.com/for-partners. What I get is that readers who write to me get an answer, which is the only thing that makes the site worth running. If you would rather not, one line saying so is enough and I will not write again. Alex Bandziuk moveandinvest.com · office@moveandinvest.com | R6: не отправлено | T6: =IF(S6="","",S6+14)
A7: 2 | B7: Португалия | C7: юрфирма | D7: PLMJ | E7: plmj.com | G7: email | H7: plmjlaw@plmj.pt | I7: полносервисная коммерческая | J7: НЕТ в практиках | K7: не проверялся | L7: PT, EN | M7: B | N7: бесплатная — закон | O7: Enquiries about the Portuguese Golden Visa — no fee either way | P7: Hello, My name is Alex Bandziuk. I run moveandinvest.com, an independent comparison of residency-by-investment routes in Portugal, Greece, Malta, the UAE and Cyprus. I am not an agency and I sell none of these programmes. I am writing to ask whether you would take enquiries from readers asking about your jurisdiction. No money passes in either direction, and that is deliberate rather than generous: your professional rules do not permit paying for an introduced client, so I ask for nothing and you would owe nothing. An enquiry is one person who filled in six fields in their own words — the country, a budget ceiling, a timeline, the goal, a free-text paragraph, a name and an email — and gave explicit consent to be passed to a single adviser. One firm per jurisdiction, never resold, never sent to two firms. The form is at moveandinvest.com/for-partners. What I get is that readers who write to me get an answer, which is the only thing that makes the site worth running. If you would rather not, one line saying so is enough and I will not write again. Alex Bandziuk moveandinvest.com · office@moveandinvest.com | R7: не отправлено | T7: =IF(S7="","",S7+14)
A8: 2 | B8: Португалия | C8: юрфирма | D8: RFF Lawyers | E8: rfflawyers.com | F8: Rogério Fernandes Ferreira | G8: форма | H8: https://www.rfflawyers.com/en/contacts/ | I8: налогово-бизнесовый бутик | J8: НЕТ в практиках | K8: cédula 8074L не открылась | L8: PT, EN | M8: B | N8: бесплатная — закон | O8: Enquiries about the Portuguese Golden Visa — no fee either way | P8: Hello, My name is Alex Bandziuk. I run moveandinvest.com, an independent comparison of residency-by-investment routes in Portugal, Greece, Malta, the UAE and Cyprus. I am not an agency and I sell none of these programmes. I am writing to ask whether you would take enquiries from readers asking about your jurisdiction. No money passes in either direction, and that is deliberate rather than generous: your professional rules do not permit paying for an introduced client, so I ask for nothing and you would owe nothing. An enquiry is one person who filled in six fields in their own words — the country, a budget ceiling, a timeline, the goal, a free-text paragraph, a name and an email — and gave explicit consent to be passed to a single adviser. One firm per jurisdiction, never resold, never sent to two firms. The form is at moveandinvest.com/for-partners. What I get is that readers who write to me get an answer, which is the only thing that makes the site worth running. If you would rather not, one line saying so is enough and I will not write again. Alex Bandziuk moveandinvest.com · office@moveandinvest.com | Q8: Лучший контент рынка, но иммиграции в практиках нет. | R8: не отправлено | T8: =IF(S8="","",S8+14)
A9: 2 | B9: Португалия | C9: юрфирма | D9: Morais Leitão (MLGTS) | E9: mlgts.pt | G9: форма | H9: https://www.mlgts.pt/en/about-us/contacts/ | I9: полносервисная коммерческая | J9: да — в составе трудовой практики | K9: не проверялся | L9: PT, EN | M9: B | N9: бесплатная — закон | O9: Enquiries about the Portuguese Golden Visa — no fee either way | P9: Hello, My name is Alex Bandziuk. I run moveandinvest.com, an independent comparison of residency-by-investment routes in Portugal, Greece, Malta, the UAE and Cyprus. I am not an agency and I sell none of these programmes. I am writing to ask whether you would take enquiries from readers asking about your jurisdiction. No money passes in either direction, and that is deliberate rather than generous: your professional rules do not permit paying for an introduced client, so I ask for nothing and you would owe nothing. An enquiry is one person who filled in six fields in their own words — the country, a budget ceiling, a timeline, the goal, a free-text paragraph, a name and an email — and gave explicit consent to be passed to a single adviser. One firm per jurisdiction, never resold, never sent to two firms. The form is at moveandinvest.com/for-partners. What I get is that readers who write to me get an answer, which is the only thing that makes the site worth running. If you would rather not, one line saying so is enough and I will not write again. Alex Bandziuk moveandinvest.com · office@moveandinvest.com | R9: не отправлено | T9: =IF(S9="","",S9+14)
A10: 1 | B10: Португалия | C10: не юрфирма | D10: DRP Advisers | E10: drpadvisers.com | F10: David Rabi — Founder | G10: email | H10: info@drpadvisers.com | I10: недвижимость + консультанты по Golden Visa | J10: да | K10: AMI 21431 (IMPIC) | L10: EN, PT | M10: A | N10: платная | O10: Enquiries about the Portuguese Golden Visa — on what terms? | P10: Hello, My name is Alex Bandziuk. I run moveandinvest.com, an independent comparison of residency-by-investment routes in Portugal, Greece, Malta, the UAE and Cyprus. I am not an agency and I sell none of these programmes. One question: does your firm pay for enquiries of this kind, and on what basis — per lead, per consultation, per signed client? You would name the terms; there is no price list on my side. An enquiry is one person who filled in six fields in their own words — the country, a budget ceiling, a timeline, the goal, a free-text paragraph, a name and an email — and gave explicit consent to be passed to a single adviser. One firm per jurisdiction: leads are never resold and never sent to two firms. The form is at moveandinvest.com/for-partners. If the answer is no, one line saying so is enough and I will not write again. Alex Bandziuk moveandinvest.com · office@moveandinvest.com | Q10: Лицензия опубликована. | R10: не отправлено | T10: =IF(S10="","",S10+14)
A11: 1 | B11: Португалия | C11: не юрфирма | D11: Goldcrest Advisers | E11: portugalbuyersagent.com | F11: Patricia Casaburi — MD | G11: email | H11: info@portugalbuyersagent.com | I11: независимый байерс-агент | J11: да | K11: AMI-23310 | L11: EN, PT | M11: A | N11: платная | O11: Enquiries about the Portuguese Golden Visa — on what terms? | P11: Hello, My name is Alex Bandziuk. I run moveandinvest.com, an independent comparison of residency-by-investment routes in Portugal, Greece, Malta, the UAE and Cyprus. I am not an agency and I sell none of these programmes. One question: does your firm pay for enquiries of this kind, and on what basis — per lead, per consultation, per signed client? You would name the terms; there is no price list on my side. An enquiry is one person who filled in six fields in their own words — the country, a budget ceiling, a timeline, the goal, a free-text paragraph, a name and an email — and gave explicit consent to be passed to a single adviser. One firm per jurisdiction: leads are never resold and never sent to two firms. The form is at moveandinvest.com/for-partners. If the answer is no, one line saying so is enough and I will not write again. Alex Bandziuk moveandinvest.com · office@moveandinvest.com | Q11: «Portugal's first independent buyer's agent». | R11: не отправлено | T11: =IF(S11="","",S11+14)
A12: 2 | B12: Португалия | C12: не юрфирма | D12: The Buyer's Agent Portugal | E12: thebuyersagentportugal.com | F12: Maya de Filippo — Founder | G12: email | H12: info@thebuyersagentportugal.com | I12: байерс-агент для иностранцев | J12: да | K12: AMI 23932 | L12: EN | M12: A | N12: платная | O12: Enquiries about the Portuguese Golden Visa — on what terms? | P12: Hello, My name is Alex Bandziuk. I run moveandinvest.com, an independent comparison of residency-by-investment routes in Portugal, Greece, Malta, the UAE and Cyprus. I am not an agency and I sell none of these programmes. One question: does your firm pay for enquiries of this kind, and on what basis — per lead, per consultation, per signed client? You would name the terms; there is no price list on my side. An enquiry is one person who filled in six fields in their own words — the country, a budget ceiling, a timeline, the goal, a free-text paragraph, a name and an email — and gave explicit consent to be passed to a single adviser. One firm per jurisdiction: leads are never resold and never sent to two firms. The form is at moveandinvest.com/for-partners. If the answer is no, one line saying so is enough and I will not write again. Alex Bandziuk moveandinvest.com · office@moveandinvest.com | R12: не отправлено | T12: =IF(S12="","",S12+14)
A13: 2 | B13: Португалия | C13: не юрфирма | D13: VIDA Capital | E13: vida-cap.com | F13: José Covas — CIO | G13: email | H13: ir@vida-cap.com | I13: фонд: гостиничные активы под ВНЖ | J13: да | K13: рег. номер не опубликован; фонд под STAG SCR (CMVM) | L13: EN | M13: A | N13: платная | O13: Enquiries about the Portuguese Golden Visa — on what terms? | P13: Hello, My name is Alex Bandziuk. I run moveandinvest.com, an independent comparison of residency-by-investment routes in Portugal, Greece, Malta, the UAE and Cyprus. I am not an agency and I sell none of these programmes. One question: does your firm pay for enquiries of this kind, and on what basis — per lead, per consultation, per signed client? You would name the terms; there is no price list on my side. An enquiry is one person who filled in six fields in their own words — the country, a budget ceiling, a timeline, the goal, a free-text paragraph, a name and an email — and gave explicit consent to be passed to a single adviser. One firm per jurisdiction: leads are never resold and never sent to two firms. The form is at moveandinvest.com/for-partners. If the answer is no, one line saying so is enough and I will not write again. Alex Bandziuk moveandinvest.com · office@moveandinvest.com | Q13: Фондовый маршрут — единственный действующий в Португалии. Дистрибуционные комиссии там норма. | R13: не отправлено | T13: =IF(S13="","",S13+14)
A14: 2 | B14: Португалия | C14: не юрфирма | D14: Visas.pt | E14: visas.pt | F14: Jessica Oliveira — Immigration Lawyer | G14: email | H14: contact@visas.pt | I14: визовый сервис, «lawyer-backed» | J14: да | K14: не опубликован | L14: EN, PT | M14: A | N14: платная | O14: Enquiries about the Portuguese Golden Visa — on what terms? | P14: Hello, My name is Alex Bandziuk. I run moveandinvest.com, an independent comparison of residency-by-investment routes in Portugal, Greece, Malta, the UAE and Cyprus. I am not an agency and I sell none of these programmes. One question: does your firm pay for enquiries of this kind, and on what basis — per lead, per consultation, per signed client? You would name the terms; there is no price list on my side. An enquiry is one person who filled in six fields in their own words — the country, a budget ceiling, a timeline, the goal, a free-text paragraph, a name and an email — and gave explicit consent to be passed to a single adviser. One firm per jurisdiction: leads are never resold and never sent to two firms. The form is at moveandinvest.com/for-partners. If the answer is no, one line saying so is enough and I will not write again. Alex Bandziuk moveandinvest.com · office@moveandinvest.com | Q14: «Lawyer-backed» — не адвокатская практика, но проверить, кто подписывает. | R14: не отправлено | T14: =IF(S14="","",S14+14)
A15: 2 | B15: Португалия | C15: не юрфирма | D15: MoveTo Relocation Agency | E15: moveto.agency | F15: Yurchyk Yurii — CEO | G15: email | H15: info@movetocascais.com | I15: релокационное агентство, Эшторил | J15: да | K15: не опубликован | L15: EN, PT, RU? | M15: A | N15: платная | O15: Enquiries about the Portuguese Golden Visa — on what terms? | P15: Hello, My name is Alex Bandziuk. I run moveandinvest.com, an independent comparison of residency-by-investment routes in Portugal, Greece, Malta, the UAE and Cyprus. I am not an agency and I sell none of these programmes. One question: does your firm pay for enquiries of this kind, and on what basis — per lead, per consultation, per signed client? You would name the terms; there is no price list on my side. An enquiry is one person who filled in six fields in their own words — the country, a budget ceiling, a timeline, the goal, a free-text paragraph, a name and an email — and gave explicit consent to be passed to a single adviser. One firm per jurisdiction: leads are never resold and never sent to two firms. The form is at moveandinvest.com/for-partners. If the answer is no, one line saying so is enough and I will not write again. Alex Bandziuk moveandinvest.com · office@moveandinvest.com | Q15: Язык не подтверждён, имя владельца славянское. | R15: не отправлено | T15: =IF(S15="","",S15+14)
A16: 2 | B16: Португалия | C16: не юрфирма | D16: New Way — Visa & Relocation | E16: newway.pt | F16: Carlos Baltasar — CEO | G16: форма | H16: https://newway.pt/en/ | I16: визы и релокация | J16: да — D2, не ARI | K16: не опубликован | L16: EN, PT | M16: A | N16: платная | O16: Enquiries about the Portuguese Golden Visa — on what terms? | P16: Hello, My name is Alex Bandziuk. I run moveandinvest.com, an independent comparison of residency-by-investment routes in Portugal, Greece, Malta, the UAE and Cyprus. I am not an agency and I sell none of these programmes. One question: does your firm pay for enquiries of this kind, and on what basis — per lead, per consultation, per signed client? You would name the terms; there is no price list on my side. An enquiry is one person who filled in six fields in their own words — the country, a budget ceiling, a timeline, the goal, a free-text paragraph, a name and an email — and gave explicit consent to be passed to a single adviser. One firm per jurisdiction: leads are never resold and never sent to two firms. The form is at moveandinvest.com/for-partners. If the answer is no, one line saying so is enough and I will not write again. Alex Bandziuk moveandinvest.com · office@moveandinvest.com | Q16: Ящика нет, только телефон. | R16: не отправлено | T16: =IF(S16="","",S16+14)
A17: 2 | B17: Португалия | C17: не юрфирма | D17: Portugal Pathways | E17: portugalpathways.io | F17: Paul Stannard — Chairman | G17: форма | H17: https://www.portugalpathways.io/contact | I17: визы, недвижимость, налоги, консьерж | J17: да | K17: не опубликован | L17: EN | M17: A | N17: платная | O17: Enquiries about the Portuguese Golden Visa — on what terms? | P17: Hello, My name is Alex Bandziuk. I run moveandinvest.com, an independent comparison of residency-by-investment routes in Portugal, Greece, Malta, the UAE and Cyprus. I am not an agency and I sell none of these programmes. One question: does your firm pay for enquiries of this kind, and on what basis — per lead, per consultation, per signed client? You would name the terms; there is no price list on my side. An enquiry is one person who filled in six fields in their own words — the country, a budget ceiling, a timeline, the goal, a free-text paragraph, a name and an email — and gave explicit consent to be passed to a single adviser. One firm per jurisdiction: leads are never resold and never sent to two firms. The form is at moveandinvest.com/for-partners. If the answer is no, one line saying so is enough and I will not write again. Alex Bandziuk moveandinvest.com · office@moveandinvest.com | R17: не отправлено | T17: =IF(S17="","",S17+14)
A18: 1 | B18: Греция | C18: юрфирма | D18: Tsiricos Law Office | E18: tsiricos.gr | F18: Takis Th. Tsiricos | G18: email | H18: info@tsiricos.gr | I18: бутик: недвижимость, golden visa | J18: да | K18: реестр не открывался | L18: EN, GR | M18: A | N18: платная | O18: Enquiries about the Greek Golden Visa — on what terms? | P18: Hello, My name is Alex Bandziuk. I run moveandinvest.com, an independent comparison of residency-by-investment routes in Portugal, Greece, Malta, the UAE and Cyprus. I am not an agency and I sell none of these programmes. One question: does your firm pay for enquiries of this kind, and on what basis — per lead, per consultation, per signed client? You would name the terms; there is no price list on my side. An enquiry is one person who filled in six fields in their own words — the country, a budget ceiling, a timeline, the goal, a free-text paragraph, a name and an email — and gave explicit consent to be passed to a single adviser. One firm per jurisdiction: leads are never resold and never sent to two firms. The form is at moveandinvest.com/for-partners. If the answer is no, one line saying so is enough and I will not write again. Alex Bandziuk moveandinvest.com · office@moveandinvest.com | Q18: Самый точный греческий контент. | R18: не отправлено | T18: =IF(S18="","",S18+14)
A19: 1 | B19: Греция | C19: юрфирма | D19: Georgaki & Partners | E19: georgakilawfirm.com | F19: Christina Georgaki | G19: email | H19: info@georgakilawfirm.com | I19: многопрофильная, сильный golden visa | J19: да — заявляют 6000 ВНЖ | K19: реестр не открывался | L19: EN, GR, RU, TR, DE, FR, HE | M19: A | N19: платная | O19: Enquiries about the Greek Golden Visa — on what terms? | P19: Hello, My name is Alex Bandziuk. I run moveandinvest.com, an independent comparison of residency-by-investment routes in Portugal, Greece, Malta, the UAE and Cyprus. I am not an agency and I sell none of these programmes. One question: does your firm pay for enquiries of this kind, and on what basis — per lead, per consultation, per signed client? You would name the terms; there is no price list on my side. An enquiry is one person who filled in six fields in their own words — the country, a budget ceiling, a timeline, the goal, a free-text paragraph, a name and an email — and gave explicit consent to be passed to a single adviser. One firm per jurisdiction: leads are never resold and never sent to two firms. The form is at moveandinvest.com/for-partners. If the answer is no, one line saying so is enough and I will not write again. Alex Bandziuk moveandinvest.com · office@moveandinvest.com | Q19: Русский подтверждён. Единственный такой кандидат в Греции. | R19: не отправлено | T19: =IF(S19="","",S19+14)
A20: 1 | B20: Греция | C20: юрфирма | D20: Risvas & Associates | E20: risvaslaw.gr | G20: email | H20: info@risvaslaw.gr | I20: бутик, инвестиционная миграция | J20: да | K20: адрес совпал с прошлой проверкой | L20: EN, GR | M20: A | N20: платная | O20: Enquiries about the Greek Golden Visa — on what terms? | P20: Hello, My name is Alex Bandziuk. I run moveandinvest.com, an independent comparison of residency-by-investment routes in Portugal, Greece, Malta, the UAE and Cyprus. I am not an agency and I sell none of these programmes. One question: does your firm pay for enquiries of this kind, and on what basis — per lead, per consultation, per signed client? You would name the terms; there is no price list on my side. An enquiry is one person who filled in six fields in their own words — the country, a budget ceiling, a timeline, the goal, a free-text paragraph, a name and an email — and gave explicit consent to be passed to a single adviser. One firm per jurisdiction: leads are never resold and never sent to two firms. The form is at moveandinvest.com/for-partners. If the answer is no, one line saying so is enough and I will not write again. Alex Bandziuk moveandinvest.com · office@moveandinvest.com | R20: не отправлено | T20: =IF(S20="","",S20+14)
A21: 2 | B21: Греция | C21: юрфирма | D21: Valmas Associates | E21: athenslawoffice.com | G21: email | H21: info@athenslawoffice.com | I21: недвижимость и иммиграция | J21: да | K21: лицензия 30492 — самопубликация | L21: EN, GR | M21: A | N21: платная | O21: Enquiries about the Greek Golden Visa — on what terms? | P21: Hello, My name is Alex Bandziuk. I run moveandinvest.com, an independent comparison of residency-by-investment routes in Portugal, Greece, Malta, the UAE and Cyprus. I am not an agency and I sell none of these programmes. One question: does your firm pay for enquiries of this kind, and on what basis — per lead, per consultation, per signed client? You would name the terms; there is no price list on my side. An enquiry is one person who filled in six fields in their own words — the country, a budget ceiling, a timeline, the goal, a free-text paragraph, a name and an email — and gave explicit consent to be passed to a single adviser. One firm per jurisdiction: leads are never resold and never sent to two firms. The form is at moveandinvest.com/for-partners. If the answer is no, one line saying so is enough and I will not write again. Alex Bandziuk moveandinvest.com · office@moveandinvest.com | R21: не отправлено | T21: =IF(S21="","",S21+14)
A22: 2 | B22: Греция | C22: юрфирма | D22: Hellenic Law Firm | E22: helleniclawfirm.com | G22: email | H22: info@helleniclawfirm.com | I22: бутик для состоятельных, 3 партнёра | J22: да | K22: не проверялся | L22: EN, GR | M22: A | N22: платная | O22: Enquiries about the Greek Golden Visa — on what terms? | P22: Hello, My name is Alex Bandziuk. I run moveandinvest.com, an independent comparison of residency-by-investment routes in Portugal, Greece, Malta, the UAE and Cyprus. I am not an agency and I sell none of these programmes. One question: does your firm pay for enquiries of this kind, and on what basis — per lead, per consultation, per signed client? You would name the terms; there is no price list on my side. An enquiry is one person who filled in six fields in their own words — the country, a budget ceiling, a timeline, the goal, a free-text paragraph, a name and an email — and gave explicit consent to be passed to a single adviser. One firm per jurisdiction: leads are never resold and never sent to two firms. The form is at moveandinvest.com/for-partners. If the answer is no, one line saying so is enough and I will not write again. Alex Bandziuk moveandinvest.com · office@moveandinvest.com | R22: не отправлено | T22: =IF(S22="","",S22+14)
A23: 2 | B23: Греция | C23: юрфирма | D23: Varnavas Law | E23: varnavas.gr | G23: email | H23: legal@varnavas.gr | I23: полносервисный бутик, «Golden Visa Desk» | J23: да | K23: не проверялся | L23: EN, GR | M23: A | N23: платная | O23: Enquiries about the Greek Golden Visa — on what terms? | P23: Hello, My name is Alex Bandziuk. I run moveandinvest.com, an independent comparison of residency-by-investment routes in Portugal, Greece, Malta, the UAE and Cyprus. I am not an agency and I sell none of these programmes. One question: does your firm pay for enquiries of this kind, and on what basis — per lead, per consultation, per signed client? You would name the terms; there is no price list on my side. An enquiry is one person who filled in six fields in their own words — the country, a budget ceiling, a timeline, the goal, a free-text paragraph, a name and an email — and gave explicit consent to be passed to a single adviser. One firm per jurisdiction: leads are never resold and never sent to two firms. The form is at moveandinvest.com/for-partners. If the answer is no, one line saying so is enough and I will not write again. Alex Bandziuk moveandinvest.com · office@moveandinvest.com | Q23: Пересечение по трафику есть. | R23: не отправлено | T23: =IF(S23="","",S23+14)
A24: 2 | B24: Греция | C24: юрфирма | D24: Amoiridis Law Services | E24: law-services.gr | F24: Charalampos F. Amoiridis | G24: форма | H24: https://www.law-services.gr/contact-alternative/ | I24: споры и услуги иностранцам | J24: да | K24: номера коллегии нет | L24: EN, GR, RU | M24: A | N24: платная | O24: Enquiries about the Greek Golden Visa — on what terms? | P24: Hello, My name is Alex Bandziuk. I run moveandinvest.com, an independent comparison of residency-by-investment routes in Portugal, Greece, Malta, the UAE and Cyprus. I am not an agency and I sell none of these programmes. One question: does your firm pay for enquiries of this kind, and on what basis — per lead, per consultation, per signed client? You would name the terms; there is no price list on my side. An enquiry is one person who filled in six fields in their own words — the country, a budget ceiling, a timeline, the goal, a free-text paragraph, a name and an email — and gave explicit consent to be passed to a single adviser. One firm per jurisdiction: leads are never resold and never sent to two firms. The form is at moveandinvest.com/for-partners. If the answer is no, one line saying so is enough and I will not write again. Alex Bandziuk moveandinvest.com · office@moveandinvest.com | Q24: Адвокаты названы, номера — нет. | R24: не отправлено | T24: =IF(S24="","",S24+14)
A25: 1 | B25: Греция | C25: не юрфирма | D25: Ellas Estate DS Group AE | E25: ellasestate.com | F25: Damianos Sachmpazidis — Chairman | G25: email | H25: info@ellasestate.com | I25: недвижимость + сопровождение Golden Visa | J25: да | K25: ΓΕΜΗ 181608506000, ΑΦΜ 802724638 | L25: EN, GR | M25: A | N25: платная | O25: Enquiries about the Greek Golden Visa — on what terms? | P25: Hello, My name is Alex Bandziuk. I run moveandinvest.com, an independent comparison of residency-by-investment routes in Portugal, Greece, Malta, the UAE and Cyprus. I am not an agency and I sell none of these programmes. One question: does your firm pay for enquiries of this kind, and on what basis — per lead, per consultation, per signed client? You would name the terms; there is no price list on my side. An enquiry is one person who filled in six fields in their own words — the country, a budget ceiling, a timeline, the goal, a free-text paragraph, a name and an email — and gave explicit consent to be passed to a single adviser. One firm per jurisdiction: leads are never resold and never sent to two firms. The form is at moveandinvest.com/for-partners. If the answer is no, one line saying so is enough and I will not write again. Alex Bandziuk moveandinvest.com · office@moveandinvest.com | Q25: Регистрация опубликована полностью. | R25: не отправлено | T25: =IF(S25="","",S25+14)
A26: 2 | B26: Греция | C26: не юрфирма | D26: Golden Visa Greece (Energopiisi SA) | E26: goldenvisa-greece.com | F26: Mary Tsiganou — CEO | G26: email | H26: info@goldenvisa-greece.com | I26: инвестиции и управление в Греции | J26: да | K26: CRN 120005201000 | L26: EN, GR | M26: A | N26: платная | O26: Enquiries about the Greek Golden Visa — on what terms? | P26: Hello, My name is Alex Bandziuk. I run moveandinvest.com, an independent comparison of residency-by-investment routes in Portugal, Greece, Malta, the UAE and Cyprus. I am not an agency and I sell none of these programmes. One question: does your firm pay for enquiries of this kind, and on what basis — per lead, per consultation, per signed client? You would name the terms; there is no price list on my side. An enquiry is one person who filled in six fields in their own words — the country, a budget ceiling, a timeline, the goal, a free-text paragraph, a name and an email — and gave explicit consent to be passed to a single adviser. One firm per jurisdiction: leads are never resold and never sent to two firms. The form is at moveandinvest.com/for-partners. If the answer is no, one line saying so is enough and I will not write again. Alex Bandziuk moveandinvest.com · office@moveandinvest.com | R26: не отправлено | T26: =IF(S26="","",S26+14)
A27: 2 | B27: Греция | C27: не юрфирма | D27: Adonis Group | E27: adonisgroup.gr | F27: Dr Meisam Sabour — CEO | G27: email | H27: consultant@adoniss.gr | I27: недвижимость и ВНЖ через покупку | J27: да | K27: не опубликован | L27: EN, GR, FA? | M27: A | N27: платная | O27: Enquiries about the Greek Golden Visa — on what terms? | P27: Hello, My name is Alex Bandziuk. I run moveandinvest.com, an independent comparison of residency-by-investment routes in Portugal, Greece, Malta, the UAE and Cyprus. I am not an agency and I sell none of these programmes. One question: does your firm pay for enquiries of this kind, and on what basis — per lead, per consultation, per signed client? You would name the terms; there is no price list on my side. An enquiry is one person who filled in six fields in their own words — the country, a budget ceiling, a timeline, the goal, a free-text paragraph, a name and an email — and gave explicit consent to be passed to a single adviser. One firm per jurisdiction: leads are never resold and never sent to two firms. The form is at moveandinvest.com/for-partners. If the answer is no, one line saying so is enough and I will not write again. Alex Bandziuk moveandinvest.com · office@moveandinvest.com | Q27: ВНИМАНИЕ: домен почты adoniss.gr не совпадает с сайтом adonisgroup.gr — проверить вручную. | R27: не отправлено | T27: =IF(S27="","",S27+14)
A28: 2 | B28: Греция | C28: не юрфирма | D28: Vista Estate | E28: vistaestate.gr | F28: Giorgos Gavriilidis — MD | G28: email | H28: info@vistaestate.gr | I28: девелопмент и управление активами | J28: да | K28: 182340104000 (формат ΓΕΜΗ, не подтверждён) | L28: EN, GR | M28: A | N28: платная | O28: Enquiries about the Greek Golden Visa — on what terms? | P28: Hello, My name is Alex Bandziuk. I run moveandinvest.com, an independent comparison of residency-by-investment routes in Portugal, Greece, Malta, the UAE and Cyprus. I am not an agency and I sell none of these programmes. One question: does your firm pay for enquiries of this kind, and on what basis — per lead, per consultation, per signed client? You would name the terms; there is no price list on my side. An enquiry is one person who filled in six fields in their own words — the country, a budget ceiling, a timeline, the goal, a free-text paragraph, a name and an email — and gave explicit consent to be passed to a single adviser. One firm per jurisdiction: leads are never resold and never sent to two firms. The form is at moveandinvest.com/for-partners. If the answer is no, one line saying so is enough and I will not write again. Alex Bandziuk moveandinvest.com · office@moveandinvest.com | R28: не отправлено | T28: =IF(S28="","",S28+14)
A29: 2 | B29: Греция | C29: не юрфирма | D29: GL Real Estate | E29: glrealestate.gr | F29: Grigoris Latsios — Founder | G29: email | H29: grigorislatsios@glrealestate.gr | I29: риэлторское бюро (μεσιτικό γραφείο) | J29: да | K29: ΓΕΜΗ 165319006000 | L29: GR, EN | M29: A | N29: платная | O29: Enquiries about the Greek Golden Visa — on what terms? | P29: Hello, My name is Alex Bandziuk. I run moveandinvest.com, an independent comparison of residency-by-investment routes in Portugal, Greece, Malta, the UAE and Cyprus. I am not an agency and I sell none of these programmes. One question: does your firm pay for enquiries of this kind, and on what basis — per lead, per consultation, per signed client? You would name the terms; there is no price list on my side. An enquiry is one person who filled in six fields in their own words — the country, a budget ceiling, a timeline, the goal, a free-text paragraph, a name and an email — and gave explicit consent to be passed to a single adviser. One firm per jurisdiction: leads are never resold and never sent to two firms. The form is at moveandinvest.com/for-partners. If the answer is no, one line saying so is enough and I will not write again. Alex Bandziuk moveandinvest.com · office@moveandinvest.com | Q29: Адрес личный, не общий. | R29: не отправлено | T29: =IF(S29="","",S29+14)
A30: 2 | B30: Греция | C30: не юрфирма | D30: Cityhabitat Greece | E30: cityhabitat.gr | F30: Nikos Sepentzis — Founder | G30: не найден | I30: недвижимость под Golden Visa, с 2004 | J30: да | K30: не опубликован | L30: EN, GR | M30: A | N30: платная | O30: Enquiries about the Greek Golden Visa — on what terms? | P30: Hello, My name is Alex Bandziuk. I run moveandinvest.com, an independent comparison of residency-by-investment routes in Portugal, Greece, Malta, the UAE and Cyprus. I am not an agency and I sell none of these programmes. One question: does your firm pay for enquiries of this kind, and on what basis — per lead, per consultation, per signed client? You would name the terms; there is no price list on my side. An enquiry is one person who filled in six fields in their own words — the country, a budget ceiling, a timeline, the goal, a free-text paragraph, a name and an email — and gave explicit consent to be passed to a single adviser. One firm per jurisdiction: leads are never resold and never sent to two firms. The form is at moveandinvest.com/for-partners. If the answer is no, one line saying so is enough and I will not write again. Alex Bandziuk moveandinvest.com · office@moveandinvest.com | Q30: Адреса и формы найти не удалось. | R30: не отправлено | T30: =IF(S30="","",S30+14)
A31: 2 | B31: Греция | C31: не юрфирма | D31: Golden Visa Experts | E31: goldenvisaexperts.com | F31: Theo Groutsis — licensed agent | G31: не найден | I31: консультации по недвижимости и визам | J31: да | K31: не опубликован | L31: EN, GR | M31: A | N31: платная | O31: Enquiries about the Greek Golden Visa — on what terms? | P31: Hello, My name is Alex Bandziuk. I run moveandinvest.com, an independent comparison of residency-by-investment routes in Portugal, Greece, Malta, the UAE and Cyprus. I am not an agency and I sell none of these programmes. One question: does your firm pay for enquiries of this kind, and on what basis — per lead, per consultation, per signed client? You would name the terms; there is no price list on my side. An enquiry is one person who filled in six fields in their own words — the country, a budget ceiling, a timeline, the goal, a free-text paragraph, a name and an email — and gave explicit consent to be passed to a single adviser. One firm per jurisdiction: leads are never resold and never sent to two firms. The form is at moveandinvest.com/for-partners. If the answer is no, one line saying so is enough and I will not write again. Alex Bandziuk moveandinvest.com · office@moveandinvest.com | Q31: Адреса найти не удалось. | R31: не отправлено | T31: =IF(S31="","",S31+14)
A32: 2 | B32: Греция | C32: не юрфирма | D32: Gate Greece Properties | E32: greece-golden-visa.com | F32: Giannis Mantonanakis — MD | G32: email | H32: enquiry@greece-properties-gate.com | I32: агентство недвижимости | J32: да | K32: не опубликован | L32: EN, GR | M32: A | N32: платная | O32: Enquiries about the Greek Golden Visa — on what terms? | P32: Hello, My name is Alex Bandziuk. I run moveandinvest.com, an independent comparison of residency-by-investment routes in Portugal, Greece, Malta, the UAE and Cyprus. I am not an agency and I sell none of these programmes. One question: does your firm pay for enquiries of this kind, and on what basis — per lead, per consultation, per signed client? You would name the terms; there is no price list on my side. An enquiry is one person who filled in six fields in their own words — the country, a budget ceiling, a timeline, the goal, a free-text paragraph, a name and an email — and gave explicit consent to be passed to a single adviser. One firm per jurisdiction: leads are never resold and never sent to two firms. The form is at moveandinvest.com/for-partners. If the answer is no, one line saying so is enough and I will not write again. Alex Bandziuk moveandinvest.com · office@moveandinvest.com | Q32: В §3 документа помечены как «не юрфирма» — теперь это не дисквалификация, а тип. | R32: не отправлено | T32: =IF(S32="","",S32+14)
A33: 1 | B33: Мальта | C33: юрфирма | D33: Attard Baldacchino | E33: attardbaldacchino.com | F33: Dr Russell Attard Baldacchino | G33: email | H33: info@attardbaldacchino.com | I33: бутик: резидентство и релокация | J33: да | K33: warranted Maltese Advocate + агент RES-BALD | L33: EN + 7 языков | M33: B | N33: бесплатная — закон | O33: Enquiries about the MPRP — no fee either way | P33: Hello, My name is Alex Bandziuk. I run moveandinvest.com, an independent comparison of residency-by-investment routes in Portugal, Greece, Malta, the UAE and Cyprus. I am not an agency and I sell none of these programmes. I am writing to ask whether you would take enquiries from readers asking about your jurisdiction. No money passes in either direction, and that is deliberate rather than generous: your professional rules do not permit paying for an introduced client, so I ask for nothing and you would owe nothing. An enquiry is one person who filled in six fields in their own words — the country, a budget ceiling, a timeline, the goal, a free-text paragraph, a name and an email — and gave explicit consent to be passed to a single adviser. One firm per jurisdiction, never resold, never sent to two firms. The form is at moveandinvest.com/for-partners. What I get is that readers who write to me get an answer, which is the only thing that makes the site worth running. If you would rather not, one line saying so is enough and I will not write again. Alex Bandziuk moveandinvest.com · office@moveandinvest.com | Q33: Лучшее совпадение из всех стран. | R33: не отправлено | T33: =IF(S33="","",S33+14)
A34: 2 | B34: Мальта | C34: юрфирма | D34: Mifsud & Mifsud Advocates | E34: mifsudadvocates.com.mt | F34: Dr Malcolm Mifsud | G34: email | H34: info@mifsudadvocates.com.mt | I34: многопрофильная универсальная | J34: да | K34: агент RES-MIFS | L34: EN | M34: B | N34: бесплатная — закон | O34: Enquiries about the MPRP — no fee either way | P34: Hello, My name is Alex Bandziuk. I run moveandinvest.com, an independent comparison of residency-by-investment routes in Portugal, Greece, Malta, the UAE and Cyprus. I am not an agency and I sell none of these programmes. I am writing to ask whether you would take enquiries from readers asking about your jurisdiction. No money passes in either direction, and that is deliberate rather than generous: your professional rules do not permit paying for an introduced client, so I ask for nothing and you would owe nothing. An enquiry is one person who filled in six fields in their own words — the country, a budget ceiling, a timeline, the goal, a free-text paragraph, a name and an email — and gave explicit consent to be passed to a single adviser. One firm per jurisdiction, never resold, never sent to two firms. The form is at moveandinvest.com/for-partners. What I get is that readers who write to me get an answer, which is the only thing that makes the site worth running. If you would rather not, one line saying so is enough and I will not write again. Alex Bandziuk moveandinvest.com · office@moveandinvest.com | Q34: Прямо называют C-181/23. | R34: не отправлено | T34: =IF(S34="","",S34+14)
A35: 2 | B35: Мальта | C35: юрфирма | D35: GVZH Advocates | E35: gvzh.mt | F35: Dr Ann-Marie Bugeja | G35: email | H35: info@gvzh.mt | I35: корпоративная, >50 специалистов | J35: да | K35: агент RES-GVZH | L35: EN | M35: B | N35: бесплатная — закон | O35: Enquiries about the MPRP — no fee either way | P35: Hello, My name is Alex Bandziuk. I run moveandinvest.com, an independent comparison of residency-by-investment routes in Portugal, Greece, Malta, the UAE and Cyprus. I am not an agency and I sell none of these programmes. I am writing to ask whether you would take enquiries from readers asking about your jurisdiction. No money passes in either direction, and that is deliberate rather than generous: your professional rules do not permit paying for an introduced client, so I ask for nothing and you would owe nothing. An enquiry is one person who filled in six fields in their own words — the country, a budget ceiling, a timeline, the goal, a free-text paragraph, a name and an email — and gave explicit consent to be passed to a single adviser. One firm per jurisdiction, never resold, never sent to two firms. The form is at moveandinvest.com/for-partners. What I get is that readers who write to me get an answer, which is the only thing that makes the site worth running. If you would rather not, one line saying so is enough and I will not write again. Alex Bandziuk moveandinvest.com · office@moveandinvest.com | R35: не отправлено | T35: =IF(S35="","",S35+14)
A36: 2 | B36: Мальта | C36: юрфирма | D36: Muscat Azzopardi & Associates | E36: ma-advocates.com | F36: Dr James Muscat Azzopardi | G36: email | H36: mail@ma-advocates.com | I36: private client для HNWI | J36: да | K36: агент RES-MUSC | L36: EN | M36: B | N36: бесплатная — закон | O36: Enquiries about the MPRP — no fee either way | P36: Hello, My name is Alex Bandziuk. I run moveandinvest.com, an independent comparison of residency-by-investment routes in Portugal, Greece, Malta, the UAE and Cyprus. I am not an agency and I sell none of these programmes. I am writing to ask whether you would take enquiries from readers asking about your jurisdiction. No money passes in either direction, and that is deliberate rather than generous: your professional rules do not permit paying for an introduced client, so I ask for nothing and you would owe nothing. An enquiry is one person who filled in six fields in their own words — the country, a budget ceiling, a timeline, the goal, a free-text paragraph, a name and an email — and gave explicit consent to be passed to a single adviser. One firm per jurisdiction, never resold, never sent to two firms. The form is at moveandinvest.com/for-partners. What I get is that readers who write to me get an answer, which is the only thing that makes the site worth running. If you would rather not, one line saying so is enough and I will not write again. Alex Bandziuk moveandinvest.com · office@moveandinvest.com | R36: не отправлено | T36: =IF(S36="","",S36+14)
A37: 2 | B37: Мальта | C37: юрфирма | D37: WH Partners | E37: whpartners.eu | G37: email | H37: contact@whpartners.eu | I37: мультиюрисдикционная, регулируемые отрасли | J37: да | K37: агент RES-WHPA | L37: EN + ящик poland@ | M37: B | N37: бесплатная — закон | O37: Enquiries about the MPRP — no fee either way | P37: Hello, My name is Alex Bandziuk. I run moveandinvest.com, an independent comparison of residency-by-investment routes in Portugal, Greece, Malta, the UAE and Cyprus. I am not an agency and I sell none of these programmes. I am writing to ask whether you would take enquiries from readers asking about your jurisdiction. No money passes in either direction, and that is deliberate rather than generous: your professional rules do not permit paying for an introduced client, so I ask for nothing and you would owe nothing. An enquiry is one person who filled in six fields in their own words — the country, a budget ceiling, a timeline, the goal, a free-text paragraph, a name and an email — and gave explicit consent to be passed to a single adviser. One firm per jurisdiction, never resold, never sent to two firms. The form is at moveandinvest.com/for-partners. What I get is that readers who write to me get an answer, which is the only thing that makes the site worth running. If you would rather not, one line saying so is enough and I will not write again. Alex Bandziuk moveandinvest.com · office@moveandinvest.com | Q37: Единственный польский след во всех четырёх странах. | R37: не отправлено | T37: =IF(S37="","",S37+14)
A38: 2 | B38: Мальта | C38: юрфирма | D38: Fenech & Fenech Advocates | E38: fenechlaw.com | G38: email | H38: info@fenechlaw.com | I38: крупная полносервисная, с 1891 | J38: да | K38: агент RES-FENE | L38: EN | M38: B | N38: бесплатная — закон | O38: Enquiries about the MPRP — no fee either way | P38: Hello, My name is Alex Bandziuk. I run moveandinvest.com, an independent comparison of residency-by-investment routes in Portugal, Greece, Malta, the UAE and Cyprus. I am not an agency and I sell none of these programmes. I am writing to ask whether you would take enquiries from readers asking about your jurisdiction. No money passes in either direction, and that is deliberate rather than generous: your professional rules do not permit paying for an introduced client, so I ask for nothing and you would owe nothing. An enquiry is one person who filled in six fields in their own words — the country, a budget ceiling, a timeline, the goal, a free-text paragraph, a name and an email — and gave explicit consent to be passed to a single adviser. One firm per jurisdiction, never resold, never sent to two firms. The form is at moveandinvest.com/for-partners. What I get is that readers who write to me get an answer, which is the only thing that makes the site worth running. If you would rather not, one line saying so is enough and I will not write again. Alex Bandziuk moveandinvest.com · office@moveandinvest.com | R38: не отправлено | T38: =IF(S38="","",S38+14)
A39: 2 | B39: Мальта | C39: юрфирма | D39: GTG | E39: gtg.com.mt | G39: email | H39: info@gtg.com.mt | I39: корпоративная: финтех, M&A | J39: да | K39: агент RES-GTLG | L39: EN | M39: B | N39: бесплатная — закон | O39: Enquiries about the MPRP — no fee either way | P39: Hello, My name is Alex Bandziuk. I run moveandinvest.com, an independent comparison of residency-by-investment routes in Portugal, Greece, Malta, the UAE and Cyprus. I am not an agency and I sell none of these programmes. I am writing to ask whether you would take enquiries from readers asking about your jurisdiction. No money passes in either direction, and that is deliberate rather than generous: your professional rules do not permit paying for an introduced client, so I ask for nothing and you would owe nothing. An enquiry is one person who filled in six fields in their own words — the country, a budget ceiling, a timeline, the goal, a free-text paragraph, a name and an email — and gave explicit consent to be passed to a single adviser. One firm per jurisdiction, never resold, never sent to two firms. The form is at moveandinvest.com/for-partners. What I get is that readers who write to me get an answer, which is the only thing that makes the site worth running. If you would rather not, one line saying so is enough and I will not write again. Alex Bandziuk moveandinvest.com · office@moveandinvest.com | R39: не отправлено | T39: =IF(S39="","",S39+14)
A40: 2 | B40: Мальта | C40: юрфирма | D40: Mamo TCV Advocates | E40: mamotcv.com | G40: email | H40: info@mamotcv.com | I40: многопрофильная, финансы | J40: да | K40: агент RES-MAMO | L40: EN | M40: B | N40: бесплатная — закон | O40: Enquiries about the MPRP — no fee either way | P40: Hello, My name is Alex Bandziuk. I run moveandinvest.com, an independent comparison of residency-by-investment routes in Portugal, Greece, Malta, the UAE and Cyprus. I am not an agency and I sell none of these programmes. I am writing to ask whether you would take enquiries from readers asking about your jurisdiction. No money passes in either direction, and that is deliberate rather than generous: your professional rules do not permit paying for an introduced client, so I ask for nothing and you would owe nothing. An enquiry is one person who filled in six fields in their own words — the country, a budget ceiling, a timeline, the goal, a free-text paragraph, a name and an email — and gave explicit consent to be passed to a single adviser. One firm per jurisdiction, never resold, never sent to two firms. The form is at moveandinvest.com/for-partners. What I get is that readers who write to me get an answer, which is the only thing that makes the site worth running. If you would rather not, one line saying so is enough and I will not write again. Alex Bandziuk moveandinvest.com · office@moveandinvest.com | R40: не отправлено | T40: =IF(S40="","",S40+14)
A41: 2 | B41: Мальта | C41: юрфирма | D41: Dingli & Dingli Law Firm | E41: dingli.com.mt | G41: email | H41: info@dingli.com.mt | I41: бутик: судоходство, налоги | J41: да | K41: агент RES-DING | L41: EN | M41: B | N41: бесплатная — закон | O41: Enquiries about the MPRP — no fee either way | P41: Hello, My name is Alex Bandziuk. I run moveandinvest.com, an independent comparison of residency-by-investment routes in Portugal, Greece, Malta, the UAE and Cyprus. I am not an agency and I sell none of these programmes. I am writing to ask whether you would take enquiries from readers asking about your jurisdiction. No money passes in either direction, and that is deliberate rather than generous: your professional rules do not permit paying for an introduced client, so I ask for nothing and you would owe nothing. An enquiry is one person who filled in six fields in their own words — the country, a budget ceiling, a timeline, the goal, a free-text paragraph, a name and an email — and gave explicit consent to be passed to a single adviser. One firm per jurisdiction, never resold, never sent to two firms. The form is at moveandinvest.com/for-partners. What I get is that readers who write to me get an answer, which is the only thing that makes the site worth running. If you would rather not, one line saying so is enough and I will not write again. Alex Bandziuk moveandinvest.com · office@moveandinvest.com | R41: не отправлено | T41: =IF(S41="","",S41+14)
A42: 2 | B42: Мальта | C42: юрфирма | D42: Sciberras Advocates | E42: sciberras.legal | G42: email | H42: info@sciberras.legal | I42: бутик: иммиграция, труд | J42: да | K42: не проверялся | L42: EN | M42: B | N42: бесплатная — закон | O42: Enquiries about the MPRP — no fee either way | P42: Hello, My name is Alex Bandziuk. I run moveandinvest.com, an independent comparison of residency-by-investment routes in Portugal, Greece, Malta, the UAE and Cyprus. I am not an agency and I sell none of these programmes. I am writing to ask whether you would take enquiries from readers asking about your jurisdiction. No money passes in either direction, and that is deliberate rather than generous: your professional rules do not permit paying for an introduced client, so I ask for nothing and you would owe nothing. An enquiry is one person who filled in six fields in their own words — the country, a budget ceiling, a timeline, the goal, a free-text paragraph, a name and an email — and gave explicit consent to be passed to a single adviser. One firm per jurisdiction, never resold, never sent to two firms. The form is at moveandinvest.com/for-partners. What I get is that readers who write to me get an answer, which is the only thing that makes the site worth running. If you would rather not, one line saying so is enough and I will not write again. Alex Bandziuk moveandinvest.com · office@moveandinvest.com | Q42: Тот же адвокат числится за Endevio. | R42: не отправлено | T42: =IF(S42="","",S42+14)
A43: 2 | B43: Мальта | C43: юрфирма | D43: Camilleri Preziosi Advocates | E43: camilleripreziosi.com | G43: email | H43: info@camilleripreziosi.com | I43: корпоративно-финансовая | J43: НЕТ в практиках | K43: агент RES-CAMI | L43: EN | M43: B | N43: бесплатная — закон | O43: Enquiries about the MPRP — no fee either way | P43: Hello, My name is Alex Bandziuk. I run moveandinvest.com, an independent comparison of residency-by-investment routes in Portugal, Greece, Malta, the UAE and Cyprus. I am not an agency and I sell none of these programmes. I am writing to ask whether you would take enquiries from readers asking about your jurisdiction. No money passes in either direction, and that is deliberate rather than generous: your professional rules do not permit paying for an introduced client, so I ask for nothing and you would owe nothing. An enquiry is one person who filled in six fields in their own words — the country, a budget ceiling, a timeline, the goal, a free-text paragraph, a name and an email — and gave explicit consent to be passed to a single adviser. One firm per jurisdiction, never resold, never sent to two firms. The form is at moveandinvest.com/for-partners. What I get is that readers who write to me get an answer, which is the only thing that makes the site worth running. If you would rather not, one line saying so is enough and I will not write again. Alex Bandziuk moveandinvest.com · office@moveandinvest.com | R43: не отправлено | T43: =IF(S43="","",S43+14)
A44: 2 | B44: Мальта | C44: юрфирма | D44: GB Legal | E44: gblegal.org | F44: Dr Giannella Barbieri | G44: email | H44: giannella@gblegal.org | I44: малая: корпоративное, яхты | J44: НЕТ в практиках | K44: в реестре как «GB Partners» RES-GBLE, домен gbpartners.mt | L44: EN | M44: B | N44: бесплатная — закон | O44: Enquiries about the MPRP — no fee either way | P44: Hello, My name is Alex Bandziuk. I run moveandinvest.com, an independent comparison of residency-by-investment routes in Portugal, Greece, Malta, the UAE and Cyprus. I am not an agency and I sell none of these programmes. I am writing to ask whether you would take enquiries from readers asking about your jurisdiction. No money passes in either direction, and that is deliberate rather than generous: your professional rules do not permit paying for an introduced client, so I ask for nothing and you would owe nothing. An enquiry is one person who filled in six fields in their own words — the country, a budget ceiling, a timeline, the goal, a free-text paragraph, a name and an email — and gave explicit consent to be passed to a single adviser. One firm per jurisdiction, never resold, never sent to two firms. The form is at moveandinvest.com/for-partners. What I get is that readers who write to me get an answer, which is the only thing that makes the site worth running. If you would rather not, one line saying so is enough and I will not write again. Alex Bandziuk moveandinvest.com · office@moveandinvest.com | Q44: Расхождение домена и названия — проверить, одна ли это фирма. | R44: не отправлено | T44: =IF(S44="","",S44+14)
A45: 2 | B45: Мальта | C45: юрфирма | D45: Ganado Advocates | E45: ganado.com | G45: форма | H45: https://ganado.com/contact-us/ | I45: ведущая корпоративная | J45: не установлено | K45: агент RES-GANA | L45: EN | M45: B | N45: бесплатная — закон | O45: Enquiries about the MPRP — no fee either way | P45: Hello, My name is Alex Bandziuk. I run moveandinvest.com, an independent comparison of residency-by-investment routes in Portugal, Greece, Malta, the UAE and Cyprus. I am not an agency and I sell none of these programmes. I am writing to ask whether you would take enquiries from readers asking about your jurisdiction. No money passes in either direction, and that is deliberate rather than generous: your professional rules do not permit paying for an introduced client, so I ask for nothing and you would owe nothing. An enquiry is one person who filled in six fields in their own words — the country, a budget ceiling, a timeline, the goal, a free-text paragraph, a name and an email — and gave explicit consent to be passed to a single adviser. One firm per jurisdiction, never resold, never sent to two firms. The form is at moveandinvest.com/for-partners. What I get is that readers who write to me get an answer, which is the only thing that makes the site worth running. If you would rather not, one line saying so is enough and I will not write again. Alex Bandziuk moveandinvest.com · office@moveandinvest.com | R45: не отправлено | T45: =IF(S45="","",S45+14)
A46: 1 | B46: Мальта | C46: не юрфирма | D46: Yakof Agius & Associates | E46: yakofagius.com | F46: Yakof Agius | G46: email | H46: info@yakofagius.com | I46: профильный агент MPRP, только Мальта | J46: да | K46: агент RES-YAKO | L46: EN | M46: A | N46: платная | O46: Enquiries about the MPRP — on what terms? | P46: Hello, My name is Alex Bandziuk. I run moveandinvest.com, an independent comparison of residency-by-investment routes in Portugal, Greece, Malta, the UAE and Cyprus. I am not an agency and I sell none of these programmes. One question: does your firm pay for enquiries of this kind, and on what basis — per lead, per consultation, per signed client? You would name the terms; there is no price list on my side. An enquiry is one person who filled in six fields in their own words — the country, a budget ceiling, a timeline, the goal, a free-text paragraph, a name and an email — and gave explicit consent to be passed to a single adviser. One firm per jurisdiction: leads are never resold and never sent to two firms. The form is at moveandinvest.com/for-partners. If the answer is no, one line saying so is enough and I will not write again. Alex Bandziuk moveandinvest.com · office@moveandinvest.com | Q46: «The Leading Experts In Maltese Citizenship and Residence By Investment». | R46: не отправлено | T46: =IF(S46="","",S46+14)
A47: 1 | B47: Мальта | C47: не юрфирма | D47: MCAS Ltd | E47: mcas.com.mt | G47: email | H47: info@mcas.com.mt | I47: резидентство и гражданство Мальты | J47: да | K47: агент RES-MCAS | L47: EN | M47: A | N47: платная | O47: Enquiries about the MPRP — on what terms? | P47: Hello, My name is Alex Bandziuk. I run moveandinvest.com, an independent comparison of residency-by-investment routes in Portugal, Greece, Malta, the UAE and Cyprus. I am not an agency and I sell none of these programmes. One question: does your firm pay for enquiries of this kind, and on what basis — per lead, per consultation, per signed client? You would name the terms; there is no price list on my side. An enquiry is one person who filled in six fields in their own words — the country, a budget ceiling, a timeline, the goal, a free-text paragraph, a name and an email — and gave explicit consent to be passed to a single adviser. One firm per jurisdiction: leads are never resold and never sent to two firms. The form is at moveandinvest.com/for-partners. If the answer is no, one line saying so is enough and I will not write again. Alex Bandziuk moveandinvest.com · office@moveandinvest.com | R47: не отправлено | T47: =IF(S47="","",S47+14)
A48: 2 | B48: Мальта | C48: не юрфирма | D48: DZ Advisory Ltd | E48: dzadvisory.com | G48: email | H48: info@dzadvisory.com | I48: private client для HNWI и family offices | J48: да | K48: агент RES-DZAD | L48: EN | M48: A | N48: платная | O48: Enquiries about the MPRP — on what terms? | P48: Hello, My name is Alex Bandziuk. I run moveandinvest.com, an independent comparison of residency-by-investment routes in Portugal, Greece, Malta, the UAE and Cyprus. I am not an agency and I sell none of these programmes. One question: does your firm pay for enquiries of this kind, and on what basis — per lead, per consultation, per signed client? You would name the terms; there is no price list on my side. An enquiry is one person who filled in six fields in their own words — the country, a budget ceiling, a timeline, the goal, a free-text paragraph, a name and an email — and gave explicit consent to be passed to a single adviser. One firm per jurisdiction: leads are never resold and never sent to two firms. The form is at moveandinvest.com/for-partners. If the answer is no, one line saying so is enough and I will not write again. Alex Bandziuk moveandinvest.com · office@moveandinvest.com | R48: не отправлено | T48: =IF(S48="","",S48+14)
A49: 2 | B49: Мальта | C49: не юрфирма | D49: Oathbound Consultancy | E49: oathbound.eu | F49: Christian Tonna | G49: email | H49: info@oathbound.eu | I49: консультация по мальтийским маршрутам | J49: да | K49: агент RES-TONN | L49: EN | M49: A | N49: платная | O49: Enquiries about the MPRP — on what terms? | P49: Hello, My name is Alex Bandziuk. I run moveandinvest.com, an independent comparison of residency-by-investment routes in Portugal, Greece, Malta, the UAE and Cyprus. I am not an agency and I sell none of these programmes. One question: does your firm pay for enquiries of this kind, and on what basis — per lead, per consultation, per signed client? You would name the terms; there is no price list on my side. An enquiry is one person who filled in six fields in their own words — the country, a budget ceiling, a timeline, the goal, a free-text paragraph, a name and an email — and gave explicit consent to be passed to a single adviser. One firm per jurisdiction: leads are never resold and never sent to two firms. The form is at moveandinvest.com/for-partners. If the answer is no, one line saying so is enough and I will not write again. Alex Bandziuk moveandinvest.com · office@moveandinvest.com | Q49: Основатель юрист по образованию, фирма — не практика. | R49: не отправлено | T49: =IF(S49="","",S49+14)
A50: 2 | B50: Мальта | C50: не юрфирма | D50: FJVA — Francis J Vassallo & Associates | E50: fjvassallo.com | G50: email | H50: enquire@fjvassallo.com | I50: CSP под надзором MFSA | J50: да | K50: агент RES-FRAN | L50: EN | M50: A | N50: платная | O50: Enquiries about the MPRP — on what terms? | P50: Hello, My name is Alex Bandziuk. I run moveandinvest.com, an independent comparison of residency-by-investment routes in Portugal, Greece, Malta, the UAE and Cyprus. I am not an agency and I sell none of these programmes. One question: does your firm pay for enquiries of this kind, and on what basis — per lead, per consultation, per signed client? You would name the terms; there is no price list on my side. An enquiry is one person who filled in six fields in their own words — the country, a budget ceiling, a timeline, the goal, a free-text paragraph, a name and an email — and gave explicit consent to be passed to a single adviser. One firm per jurisdiction: leads are never resold and never sent to two firms. The form is at moveandinvest.com/for-partners. If the answer is no, one line saying so is enough and I will not write again. Alex Bandziuk moveandinvest.com · office@moveandinvest.com | R50: не отправлено | T50: =IF(S50="","",S50+14)
A51: 2 | B51: Мальта | C51: не юрфирма | D51: Finco Trust Services | E51: fincotrust.com | G51: email | H51: info@fincotrust.com | I51: многопрофильные проф. услуги | J51: да | K51: агент RES-FINC | L51: EN | M51: A | N51: платная | O51: Enquiries about the MPRP — on what terms? | P51: Hello, My name is Alex Bandziuk. I run moveandinvest.com, an independent comparison of residency-by-investment routes in Portugal, Greece, Malta, the UAE and Cyprus. I am not an agency and I sell none of these programmes. One question: does your firm pay for enquiries of this kind, and on what basis — per lead, per consultation, per signed client? You would name the terms; there is no price list on my side. An enquiry is one person who filled in six fields in their own words — the country, a budget ceiling, a timeline, the goal, a free-text paragraph, a name and an email — and gave explicit consent to be passed to a single adviser. One firm per jurisdiction: leads are never resold and never sent to two firms. The form is at moveandinvest.com/for-partners. If the answer is no, one line saying so is enough and I will not write again. Alex Bandziuk moveandinvest.com · office@moveandinvest.com | R51: не отправлено | T51: =IF(S51="","",S51+14)
A52: 2 | B52: Мальта | C52: не юрфирма | D52: AE Business Advisors | E52: ae.com.mt | G52: email | H52: contact@ae.com.mt | I52: корпоративные и проф. услуги | J52: да | K52: агент RES-AEAS | L52: EN | M52: A | N52: платная | O52: Enquiries about the MPRP — on what terms? | P52: Hello, My name is Alex Bandziuk. I run moveandinvest.com, an independent comparison of residency-by-investment routes in Portugal, Greece, Malta, the UAE and Cyprus. I am not an agency and I sell none of these programmes. One question: does your firm pay for enquiries of this kind, and on what basis — per lead, per consultation, per signed client? You would name the terms; there is no price list on my side. An enquiry is one person who filled in six fields in their own words — the country, a budget ceiling, a timeline, the goal, a free-text paragraph, a name and an email — and gave explicit consent to be passed to a single adviser. One firm per jurisdiction: leads are never resold and never sent to two firms. The form is at moveandinvest.com/for-partners. If the answer is no, one line saying so is enough and I will not write again. Alex Bandziuk moveandinvest.com · office@moveandinvest.com | R52: не отправлено | T52: =IF(S52="","",S52+14)
A53: 2 | B53: Мальта | C53: не юрфирма | D53: Tri-Mer Services | E53: trimerservices.com | G53: email | H53: info@trimerservices.com | I53: корпоративные услуги | J53: да | K53: агент RES-TRIM | L53: EN | M53: A | N53: платная | O53: Enquiries about the MPRP — on what terms? | P53: Hello, My name is Alex Bandziuk. I run moveandinvest.com, an independent comparison of residency-by-investment routes in Portugal, Greece, Malta, the UAE and Cyprus. I am not an agency and I sell none of these programmes. One question: does your firm pay for enquiries of this kind, and on what basis — per lead, per consultation, per signed client? You would name the terms; there is no price list on my side. An enquiry is one person who filled in six fields in their own words — the country, a budget ceiling, a timeline, the goal, a free-text paragraph, a name and an email — and gave explicit consent to be passed to a single adviser. One firm per jurisdiction: leads are never resold and never sent to two firms. The form is at moveandinvest.com/for-partners. If the answer is no, one line saying so is enough and I will not write again. Alex Bandziuk moveandinvest.com · office@moveandinvest.com | R53: не отправлено | T53: =IF(S53="","",S53+14)
A54: 2 | B54: Мальта | C54: не юрфирма | D54: CLA Malta | E54: clamalta.com | G54: email | H54: info@clamalta.com | I54: аудит, налоги, бухгалтерия | J54: да | K54: агент RES-CLAM | L54: EN | M54: A | N54: платная | O54: Enquiries about the MPRP — on what terms? | P54: Hello, My name is Alex Bandziuk. I run moveandinvest.com, an independent comparison of residency-by-investment routes in Portugal, Greece, Malta, the UAE and Cyprus. I am not an agency and I sell none of these programmes. One question: does your firm pay for enquiries of this kind, and on what basis — per lead, per consultation, per signed client? You would name the terms; there is no price list on my side. An enquiry is one person who filled in six fields in their own words — the country, a budget ceiling, a timeline, the goal, a free-text paragraph, a name and an email — and gave explicit consent to be passed to a single adviser. One firm per jurisdiction: leads are never resold and never sent to two firms. The form is at moveandinvest.com/for-partners. If the answer is no, one line saying so is enough and I will not write again. Alex Bandziuk moveandinvest.com · office@moveandinvest.com | R54: не отправлено | T54: =IF(S54="","",S54+14)
A55: 2 | B55: Мальта | C55: не юрфирма | D55: Rosemont (Malta) Ltd | E55: rosemont.com.mt | F55: S. Huxford | G55: email | H55: s.huxford@rosemont-mc.com | I55: резидентство и иммиграция через свой офис | J55: да | K55: агент RES-ROSE | L55: EN, FR | M55: A | N55: платная | O55: Enquiries about the MPRP — on what terms? | P55: Hello, My name is Alex Bandziuk. I run moveandinvest.com, an independent comparison of residency-by-investment routes in Portugal, Greece, Malta, the UAE and Cyprus. I am not an agency and I sell none of these programmes. One question: does your firm pay for enquiries of this kind, and on what basis — per lead, per consultation, per signed client? You would name the terms; there is no price list on my side. An enquiry is one person who filled in six fields in their own words — the country, a budget ceiling, a timeline, the goal, a free-text paragraph, a name and an email — and gave explicit consent to be passed to a single adviser. One firm per jurisdiction: leads are never resold and never sent to two firms. The form is at moveandinvest.com/for-partners. If the answer is no, one line saying so is enough and I will not write again. Alex Bandziuk moveandinvest.com · office@moveandinvest.com | Q55: Адрес личный; общего на сайте нет. | R55: не отправлено | T55: =IF(S55="","",S55+14)
A56: 2 | B56: Мальта | C56: не юрфирма | D56: ACT Advisory Services | E56: act.com.mt | G56: форма | H56: https://www.act.com.mt/contact-us/ | I56: advisory, corporate, tax | J56: да | K56: агент RES-ACTA | L56: EN | M56: A | N56: платная | O56: Enquiries about the MPRP — on what terms? | P56: Hello, My name is Alex Bandziuk. I run moveandinvest.com, an independent comparison of residency-by-investment routes in Portugal, Greece, Malta, the UAE and Cyprus. I am not an agency and I sell none of these programmes. One question: does your firm pay for enquiries of this kind, and on what basis — per lead, per consultation, per signed client? You would name the terms; there is no price list on my side. An enquiry is one person who filled in six fields in their own words — the country, a budget ceiling, a timeline, the goal, a free-text paragraph, a name and an email — and gave explicit consent to be passed to a single adviser. One firm per jurisdiction: leads are never resold and never sent to two firms. The form is at moveandinvest.com/for-partners. If the answer is no, one line saying so is enough and I will not write again. Alex Bandziuk moveandinvest.com · office@moveandinvest.com | Q56: Почта закрыта Cloudflare. | R56: не отправлено | T56: =IF(S56="","",S56+14)
A57: 2 | B57: Мальта | C57: не юрфирма | D57: Seed Consultancy | E57: seedconsultancy.com | G57: форма | H57: https://seedconsultancy.com/contact-us/ | I57: стратегический и policy-консалтинг | J57: да | K57: агент RES-SEED | L57: EN | M57: A | N57: платная | O57: Enquiries about the MPRP — on what terms? | P57: Hello, My name is Alex Bandziuk. I run moveandinvest.com, an independent comparison of residency-by-investment routes in Portugal, Greece, Malta, the UAE and Cyprus. I am not an agency and I sell none of these programmes. One question: does your firm pay for enquiries of this kind, and on what basis — per lead, per consultation, per signed client? You would name the terms; there is no price list on my side. An enquiry is one person who filled in six fields in their own words — the country, a budget ceiling, a timeline, the goal, a free-text paragraph, a name and an email — and gave explicit consent to be passed to a single adviser. One firm per jurisdiction: leads are never resold and never sent to two firms. The form is at moveandinvest.com/for-partners. If the answer is no, one line saying so is enough and I will not write again. Alex Bandziuk moveandinvest.com · office@moveandinvest.com | R57: не отправлено | T57: =IF(S57="","",S57+14)
A58: 2 | B58: Мальта | C58: не юрфирма | D58: NM Group Malta | E58: nmgroup.mt | G58: форма | H58: https://nmgroup.mt/contact-us/ | I58: проф. услуги «одно окно» | J58: да | K58: агент RES-NMGM | L58: EN | M58: A | N58: платная | O58: Enquiries about the MPRP — on what terms? | P58: Hello, My name is Alex Bandziuk. I run moveandinvest.com, an independent comparison of residency-by-investment routes in Portugal, Greece, Malta, the UAE and Cyprus. I am not an agency and I sell none of these programmes. One question: does your firm pay for enquiries of this kind, and on what basis — per lead, per consultation, per signed client? You would name the terms; there is no price list on my side. An enquiry is one person who filled in six fields in their own words — the country, a budget ceiling, a timeline, the goal, a free-text paragraph, a name and an email — and gave explicit consent to be passed to a single adviser. One firm per jurisdiction: leads are never resold and never sent to two firms. The form is at moveandinvest.com/for-partners. If the answer is no, one line saying so is enough and I will not write again. Alex Bandziuk moveandinvest.com · office@moveandinvest.com | R58: не отправлено | T58: =IF(S58="","",S58+14)
A59: 2 | B59: Мальта | C59: не юрфирма | D59: FACT Advisory | E59: fact.com.mt | G59: не найден | I59: бухгалтерия, аудит, налоги | J59: да | K59: агент RES-FACT | L59: EN | M59: A | N59: платная | O59: Enquiries about the MPRP — on what terms? | P59: Hello, My name is Alex Bandziuk. I run moveandinvest.com, an independent comparison of residency-by-investment routes in Portugal, Greece, Malta, the UAE and Cyprus. I am not an agency and I sell none of these programmes. One question: does your firm pay for enquiries of this kind, and on what basis — per lead, per consultation, per signed client? You would name the terms; there is no price list on my side. An enquiry is one person who filled in six fields in their own words — the country, a budget ceiling, a timeline, the goal, a free-text paragraph, a name and an email — and gave explicit consent to be passed to a single adviser. One firm per jurisdiction: leads are never resold and never sent to two firms. The form is at moveandinvest.com/for-partners. If the answer is no, one line saying so is enough and I will not write again. Alex Bandziuk moveandinvest.com · office@moveandinvest.com | Q59: Почта закрыта, страницы контактов не нашлось. | R59: не отправлено | T59: =IF(S59="","",S59+14)
A60: 2 | B60: Мальта | C60: не юрфирма | D60: Boston Malta Advisory (Boston MFO) | E60: bostonmfo.com | G60: не найден | I60: multi-family office, трасты | J60: не установлено | K60: агент RES-BOST | L60: EN | M60: A | N60: платная | O60: Enquiries about the MPRP — on what terms? | P60: Hello, My name is Alex Bandziuk. I run moveandinvest.com, an independent comparison of residency-by-investment routes in Portugal, Greece, Malta, the UAE and Cyprus. I am not an agency and I sell none of these programmes. One question: does your firm pay for enquiries of this kind, and on what basis — per lead, per consultation, per signed client? You would name the terms; there is no price list on my side. An enquiry is one person who filled in six fields in their own words — the country, a budget ceiling, a timeline, the goal, a free-text paragraph, a name and an email — and gave explicit consent to be passed to a single adviser. One firm per jurisdiction: leads are never resold and never sent to two firms. The form is at moveandinvest.com/for-partners. If the answer is no, one line saying so is enough and I will not write again. Alex Bandziuk moveandinvest.com · office@moveandinvest.com | Q60: Контента по резидентству на сайте нет вовсе. | R60: не отправлено | T60: =IF(S60="","",S60+14)
A61: 1 | B61: ОАЭ | C61: юрфирма | D61: BSA Ahmad Bin Hezeem & Associates | E61: bsalaw.com | F61: Dr Ahmad Bin Hezeem | G61: email | H61: info@bsalaw.com | I61: крупная региональная, 150 юристов | J61: НЕТ в практиках | K61: реестры требуют браузера | L61: не опубликованы | M61: B | N61: бесплатная — закон | O61: Enquiries about UAE golden residency — no fee either way | P61: Hello, My name is Alex Bandziuk. I run moveandinvest.com, an independent comparison of residency-by-investment routes in Portugal, Greece, Malta, the UAE and Cyprus. I am not an agency and I sell none of these programmes. I am writing to ask whether you would take enquiries from readers asking about your jurisdiction. No money passes in either direction, and that is deliberate rather than generous: your professional rules do not permit paying for an introduced client, so I ask for nothing and you would owe nothing. An enquiry is one person who filled in six fields in their own words — the country, a budget ceiling, a timeline, the goal, a free-text paragraph, a name and an email — and gave explicit consent to be passed to a single adviser. One firm per jurisdiction, never resold, never sent to two firms. The form is at moveandinvest.com/for-partners. What I get is that readers who write to me get an answer, which is the only thing that makes the site worth running. If you would rather not, one line saying so is enough and I will not write again. Alex Bandziuk moveandinvest.com · office@moveandinvest.com | Q61: Единственные, кто верно закрывает офф-план. | R61: не отправлено | T61: =IF(S61="","",S61+14)
A62: 2 | B62: ОАЭ | C62: юрфирма | D62: Awatif Mohammad Shoqi Advocates | E62: alrowaad.ae | F62: Awatif Al Khouri | G62: email | H62: info@alrowaad.ae | I62: полносервисная, 50+, суды | J62: НЕТ в практиках | K62: юрфирма по самоописанию | L62: EN, AR, RU | M62: B | N62: бесплатная — закон | O62: Enquiries about UAE golden residency — no fee either way | P62: Hello, My name is Alex Bandziuk. I run moveandinvest.com, an independent comparison of residency-by-investment routes in Portugal, Greece, Malta, the UAE and Cyprus. I am not an agency and I sell none of these programmes. I am writing to ask whether you would take enquiries from readers asking about your jurisdiction. No money passes in either direction, and that is deliberate rather than generous: your professional rules do not permit paying for an introduced client, so I ask for nothing and you would owe nothing. An enquiry is one person who filled in six fields in their own words — the country, a budget ceiling, a timeline, the goal, a free-text paragraph, a name and an email — and gave explicit consent to be passed to a single adviser. One firm per jurisdiction, never resold, never sent to two firms. The form is at moveandinvest.com/for-partners. What I get is that readers who write to me get an answer, which is the only thing that makes the site worth running. If you would rather not, one line saying so is enough and I will not write again. Alex Bandziuk moveandinvest.com · office@moveandinvest.com | Q62: Русский подтверждён. | R62: не отправлено | T62: =IF(S62="","",S62+14)
A63: 2 | B63: ОАЭ | C63: юрфирма | D63: Fragomen (Dubai) | E63: fragomen.com | F63: Murtaza Khan | G63: форма | H63: https://www.fragomen.com/offices/dubai-uae.html | I63: иммиграционная фирма полного цикла | J63: да — профиль целиком | K63: DIFC CL0688 | L63: EN | M63: B | N63: бесплатная — закон | O63: Enquiries about UAE golden residency — no fee either way | P63: Hello, My name is Alex Bandziuk. I run moveandinvest.com, an independent comparison of residency-by-investment routes in Portugal, Greece, Malta, the UAE and Cyprus. I am not an agency and I sell none of these programmes. I am writing to ask whether you would take enquiries from readers asking about your jurisdiction. No money passes in either direction, and that is deliberate rather than generous: your professional rules do not permit paying for an introduced client, so I ask for nothing and you would owe nothing. An enquiry is one person who filled in six fields in their own words — the country, a budget ceiling, a timeline, the goal, a free-text paragraph, a name and an email — and gave explicit consent to be passed to a single adviser. One firm per jurisdiction, never resold, never sent to two firms. The form is at moveandinvest.com/for-partners. What I get is that readers who write to me get an answer, which is the only thing that makes the site worth running. If you would rather not, one line saying so is enough and I will not write again. Alex Bandziuk moveandinvest.com · office@moveandinvest.com | Q63: Единственная в ОАЭ, где резидентство — основная практика. | R63: не отправлено | T63: =IF(S63="","",S63+14)
A64: 2 | B64: ОАЭ | C64: юрфирма | D64: Davidson & Co | E64: davidsoncolaw.com | F64: Андрей Панферов | G64: форма | H64: https://davidsoncolaw.com/contact-us/ | I64: бутик коммерческого и частного права | J64: НЕТ в практиках | K64: не проверялся | L64: EN, RU | M64: B | N64: бесплатная — закон | O64: Enquiries about UAE golden residency — no fee either way | P64: Hello, My name is Alex Bandziuk. I run moveandinvest.com, an independent comparison of residency-by-investment routes in Portugal, Greece, Malta, the UAE and Cyprus. I am not an agency and I sell none of these programmes. I am writing to ask whether you would take enquiries from readers asking about your jurisdiction. No money passes in either direction, and that is deliberate rather than generous: your professional rules do not permit paying for an introduced client, so I ask for nothing and you would owe nothing. An enquiry is one person who filled in six fields in their own words — the country, a budget ceiling, a timeline, the goal, a free-text paragraph, a name and an email — and gave explicit consent to be passed to a single adviser. One firm per jurisdiction, never resold, never sent to two firms. The form is at moveandinvest.com/for-partners. What I get is that readers who write to me get an answer, which is the only thing that makes the site worth running. If you would rather not, one line saying so is enough and I will not write again. Alex Bandziuk moveandinvest.com · office@moveandinvest.com | Q64: В mailto шаблон webmaster@example.com. | R64: не отправлено | T64: =IF(S64="","",S64+14)
A65: 1 | B65: ОАЭ | C65: не юрфирма | D65: Shuraa Business Setup | E65: shuraa.com | F65: Saeed Khalifa Mohammed Al Fuqaei — Chairman | G65: email | H65: info@shuraa.com | I65: бизнес-сетап, лицензии, визы | J65: да — Golden Visa только по ОАЭ | K65: не опубликован | L65: EN, AR, HI | M65: A | N65: платная | O65: Enquiries about UAE golden residency — on what terms? | P65: Hello, My name is Alex Bandziuk. I run moveandinvest.com, an independent comparison of residency-by-investment routes in Portugal, Greece, Malta, the UAE and Cyprus. I am not an agency and I sell none of these programmes. One question: does your firm pay for enquiries of this kind, and on what basis — per lead, per consultation, per signed client? You would name the terms; there is no price list on my side. An enquiry is one person who filled in six fields in their own words — the country, a budget ceiling, a timeline, the goal, a free-text paragraph, a name and an email — and gave explicit consent to be passed to a single adviser. One firm per jurisdiction: leads are never resold and never sent to two firms. The form is at moveandinvest.com/for-partners. If the answer is no, one line saying so is enough and I will not write again. Alex Bandziuk moveandinvest.com · office@moveandinvest.com | R65: не отправлено | T65: =IF(S65="","",S65+14)
A66: 1 | B66: ОАЭ | C66: не юрфирма | D66: TVG Consultancy | E66: tvgconsultancy.com | F66: Ansh Virmani — CEO | G66: email | H66: hello@tvgconsultancy.com | I66: сопровождение предпринимателей в ОАЭ | J66: да | K66: не опубликован | L66: EN | M66: A | N66: платная | O66: Enquiries about UAE golden residency — on what terms? | P66: Hello, My name is Alex Bandziuk. I run moveandinvest.com, an independent comparison of residency-by-investment routes in Portugal, Greece, Malta, the UAE and Cyprus. I am not an agency and I sell none of these programmes. One question: does your firm pay for enquiries of this kind, and on what basis — per lead, per consultation, per signed client? You would name the terms; there is no price list on my side. An enquiry is one person who filled in six fields in their own words — the country, a budget ceiling, a timeline, the goal, a free-text paragraph, a name and an email — and gave explicit consent to be passed to a single adviser. One firm per jurisdiction: leads are never resold and never sent to two firms. The form is at moveandinvest.com/for-partners. If the answer is no, one line saying so is enough and I will not write again. Alex Bandziuk moveandinvest.com · office@moveandinvest.com | R66: не отправлено | T66: =IF(S66="","",S66+14)
A67: 2 | B67: ОАЭ | C67: не юрфирма | D67: Consult Kumar (Team Squaree) | E67: consultkumar.com | F67: Harshaal Kumaar — CEO | G67: email | H67: harshaal@consultkumar.com | I67: бизнес-сетап и структурирование | J67: да | K67: License 1039787, Dubai | L67: EN | M67: A | N67: платная | O67: Enquiries about UAE golden residency — on what terms? | P67: Hello, My name is Alex Bandziuk. I run moveandinvest.com, an independent comparison of residency-by-investment routes in Portugal, Greece, Malta, the UAE and Cyprus. I am not an agency and I sell none of these programmes. One question: does your firm pay for enquiries of this kind, and on what basis — per lead, per consultation, per signed client? You would name the terms; there is no price list on my side. An enquiry is one person who filled in six fields in their own words — the country, a budget ceiling, a timeline, the goal, a free-text paragraph, a name and an email — and gave explicit consent to be passed to a single adviser. One firm per jurisdiction: leads are never resold and never sent to two firms. The form is at moveandinvest.com/for-partners. If the answer is no, one line saying so is enough and I will not write again. Alex Bandziuk moveandinvest.com · office@moveandinvest.com | Q67: Лицензия опубликована — редкость для ОАЭ. | R67: не отправлено | T67: =IF(S67="","",S67+14)
A68: 2 | B68: ОАЭ | C68: не юрфирма | D68: Nex Consultants | E68: nexconsultants.com | F68: Davis Kadavan — Managing Partner | G68: email | H68: info@nexconsultants.com | I68: инкорпорация и advisory | J68: да | K68: не опубликован | L68: EN | M68: A | N68: платная | O68: Enquiries about UAE golden residency — on what terms? | P68: Hello, My name is Alex Bandziuk. I run moveandinvest.com, an independent comparison of residency-by-investment routes in Portugal, Greece, Malta, the UAE and Cyprus. I am not an agency and I sell none of these programmes. One question: does your firm pay for enquiries of this kind, and on what basis — per lead, per consultation, per signed client? You would name the terms; there is no price list on my side. An enquiry is one person who filled in six fields in their own words — the country, a budget ceiling, a timeline, the goal, a free-text paragraph, a name and an email — and gave explicit consent to be passed to a single adviser. One firm per jurisdiction: leads are never resold and never sent to two firms. The form is at moveandinvest.com/for-partners. If the answer is no, one line saying so is enough and I will not write again. Alex Bandziuk moveandinvest.com · office@moveandinvest.com | R68: не отправлено | T68: =IF(S68="","",S68+14)
A69: 2 | B69: ОАЭ | C69: не юрфирма | D69: Riz & Mona Consultancy | E69: rizmona.com | F69: Rizwan Anjum Chaudhary — CEO | G69: email | H69: info@rizmona.com | I69: регистрация, лицензии, визы, банки | J69: да | K69: не опубликован | L69: EN, UR | M69: A | N69: платная | O69: Enquiries about UAE golden residency — on what terms? | P69: Hello, My name is Alex Bandziuk. I run moveandinvest.com, an independent comparison of residency-by-investment routes in Portugal, Greece, Malta, the UAE and Cyprus. I am not an agency and I sell none of these programmes. One question: does your firm pay for enquiries of this kind, and on what basis — per lead, per consultation, per signed client? You would name the terms; there is no price list on my side. An enquiry is one person who filled in six fields in their own words — the country, a budget ceiling, a timeline, the goal, a free-text paragraph, a name and an email — and gave explicit consent to be passed to a single adviser. One firm per jurisdiction: leads are never resold and never sent to two firms. The form is at moveandinvest.com/for-partners. If the answer is no, one line saying so is enough and I will not write again. Alex Bandziuk moveandinvest.com · office@moveandinvest.com | R69: не отправлено | T69: =IF(S69="","",S69+14)
A70: 2 | B70: ОАЭ | C70: не юрфирма | D70: Aurion Business Consultants | E70: aurionuae.com | F70: Syam Panayickal Prabhu — MD | G70: email | H70: contact@aurionuae.com | I70: бизнес-сетап, PRO, комплаенс | J70: да | K70: не опубликован | L70: EN | M70: A | N70: платная | O70: Enquiries about UAE golden residency — on what terms? | P70: Hello, My name is Alex Bandziuk. I run moveandinvest.com, an independent comparison of residency-by-investment routes in Portugal, Greece, Malta, the UAE and Cyprus. I am not an agency and I sell none of these programmes. One question: does your firm pay for enquiries of this kind, and on what basis — per lead, per consultation, per signed client? You would name the terms; there is no price list on my side. An enquiry is one person who filled in six fields in their own words — the country, a budget ceiling, a timeline, the goal, a free-text paragraph, a name and an email — and gave explicit consent to be passed to a single adviser. One firm per jurisdiction: leads are never resold and never sent to two firms. The form is at moveandinvest.com/for-partners. If the answer is no, one line saying so is enough and I will not write again. Alex Bandziuk moveandinvest.com · office@moveandinvest.com | R70: не отправлено | T70: =IF(S70="","",S70+14)
A71: 2 | B71: ОАЭ | C71: не юрфирма | D71: Decisive Zone | E71: decisivezone.ae | F71: Dyuti Parruck — CEO | G71: форма | H71: https://www.decisivezone.ae/ | I71: бизнес-сетап: материк, фризоны | J71: да | K71: не опубликован | L71: EN | M71: A | N71: платная | O71: Enquiries about UAE golden residency — on what terms? | P71: Hello, My name is Alex Bandziuk. I run moveandinvest.com, an independent comparison of residency-by-investment routes in Portugal, Greece, Malta, the UAE and Cyprus. I am not an agency and I sell none of these programmes. One question: does your firm pay for enquiries of this kind, and on what basis — per lead, per consultation, per signed client? You would name the terms; there is no price list on my side. An enquiry is one person who filled in six fields in their own words — the country, a budget ceiling, a timeline, the goal, a free-text paragraph, a name and an email — and gave explicit consent to be passed to a single adviser. One firm per jurisdiction: leads are never resold and never sent to two firms. The form is at moveandinvest.com/for-partners. If the answer is no, one line saying so is enough and I will not write again. Alex Bandziuk moveandinvest.com · office@moveandinvest.com | Q71: Основателя публично зовут «Mr. Golden Visa». | R71: не отправлено | T71: =IF(S71="","",S71+14)
A72: 2 | B72: ОАЭ | C72: не юрфирма | D72: Creative Zone | E72: creativezone.ae | F72: Lorenzo Jooris — CEO | G72: форма | H72: https://www.creativezone.ae/contact-us/ | I72: бизнес-сетап для МСБ | J72: да | K72: не опубликован | L72: EN | M72: A | N72: платная | O72: Enquiries about UAE golden residency — on what terms? | P72: Hello, My name is Alex Bandziuk. I run moveandinvest.com, an independent comparison of residency-by-investment routes in Portugal, Greece, Malta, the UAE and Cyprus. I am not an agency and I sell none of these programmes. One question: does your firm pay for enquiries of this kind, and on what basis — per lead, per consultation, per signed client? You would name the terms; there is no price list on my side. An enquiry is one person who filled in six fields in their own words — the country, a budget ceiling, a timeline, the goal, a free-text paragraph, a name and an email — and gave explicit consent to be passed to a single adviser. One firm per jurisdiction: leads are never resold and never sent to two firms. The form is at moveandinvest.com/for-partners. If the answer is no, one line saying so is enough and I will not write again. Alex Bandziuk moveandinvest.com · office@moveandinvest.com | R72: не отправлено | T72: =IF(S72="","",S72+14)
A73: 2 | B73: ОАЭ | C73: не юрфирма | D73: Virtuzone | E73: virtuzone.com | F73: George Hojeige — Group CEO | G73: форма | H73: https://virtuzone.com/contactus/ | I73: бизнес-сетап под ключ | J73: да | K73: не опубликован | L73: EN | M73: A | N73: платная | O73: Enquiries about UAE golden residency — on what terms? | P73: Hello, My name is Alex Bandziuk. I run moveandinvest.com, an independent comparison of residency-by-investment routes in Portugal, Greece, Malta, the UAE and Cyprus. I am not an agency and I sell none of these programmes. One question: does your firm pay for enquiries of this kind, and on what basis — per lead, per consultation, per signed client? You would name the terms; there is no price list on my side. An enquiry is one person who filled in six fields in their own words — the country, a budget ceiling, a timeline, the goal, a free-text paragraph, a name and an email — and gave explicit consent to be passed to a single adviser. One firm per jurisdiction: leads are never resold and never sent to two firms. The form is at moveandinvest.com/for-partners. If the answer is no, one line saying so is enough and I will not write again. Alex Bandziuk moveandinvest.com · office@moveandinvest.com | R73: не отправлено | T73: =IF(S73="","",S73+14)

Sheet Письма
A1: Два письма
A3: Почему писем два | B3: Плата юристу за приведённого клиента запрещена в Португалии (ст. 107 Estatuto da Ordem dos Advogados), на Мальте (Code of Ethics, ч. 2 гл. I правило 3 + Code of Police Laws, Cap. 10, ст. 42–43) и в ОАЭ (ст. 101 Federal Decree-Law 34/2022, штраф 20–200 тыс. дирхамов на ЛЮБОЕ лицо, то есть на нас). В Греции такой нормы не нашли. На не-юристов ни одна из этих норм не распространяется.
A4: Письмо A — про деньги | B4: Кому: все не-юрфирмы во всех четырёх странах + греческие юрфирмы. Спрашивает, платит ли фирма за заявки и по какой схеме.
A5: Тема A — Португалия | B5: Enquiries about the Portuguese Golden Visa — on what terms?
A6: Тема A — Греция | B6: Enquiries about the Greek Golden Visa — on what terms?
A7: Тема A — Мальта | B7: Enquiries about the MPRP — on what terms?
A8: Тема A — ОАЭ | B8: Enquiries about UAE golden residency — on what terms?
A9: Тело A | B9: Hello, My name is Alex Bandziuk. I run moveandinvest.com, an independent comparison of residency-by-investment routes in Portugal, Greece, Malta, the UAE and Cyprus. I am not an agency and I sell none of these programmes. One question: does your firm pay for enquiries of this kind, and on what basis — per lead, per consultation, per signed client? You would name the terms; there is no price list on my side. An enquiry is one person who filled in six fields in their own words — the country, a budget ceiling, a timeline, the goal, a free-text paragraph, a name and an email — and gave explicit consent to be passed to a single adviser. One firm per jurisdiction: leads are never resold and never sent to two firms. The form is at moveandinvest.com/for-partners. If the answer is no, one line saying so is enough and I will not write again. Alex Bandziuk moveandinvest.com · office@moveandinvest.com
A10: Письмо B — бесплатное | B10: Кому: юрфирмы Португалии, Мальты и ОАЭ. Денег не просит вовсе и говорит почему — иначе «бесплатно» звучит как уловка.
A11: Тема B — Португалия | B11: Enquiries about the Portuguese Golden Visa — no fee either way
A12: Тема B — Мальта | B12: Enquiries about the MPRP — no fee either way
A13: Тема B — ОАЭ | B13: Enquiries about UAE golden residency — no fee either way
A14: Тело B | B14: Hello, My name is Alex Bandziuk. I run moveandinvest.com, an independent comparison of residency-by-investment routes in Portugal, Greece, Malta, the UAE and Cyprus. I am not an agency and I sell none of these programmes. I am writing to ask whether you would take enquiries from readers asking about your jurisdiction. No money passes in either direction, and that is deliberate rather than generous: your professional rules do not permit paying for an introduced client, so I ask for nothing and you would owe nothing. An enquiry is one person who filled in six fields in their own words — the country, a budget ceiling, a timeline, the goal, a free-text paragraph, a name and an email — and gave explicit consent to be passed to a single adviser. One firm per jurisdiction, never resold, never sent to two firms. The form is at moveandinvest.com/for-partners. What I get is that readers who write to me get an answer, which is the only thing that makes the site worth running. If you would rather not, one line saying so is enough and I will not write again. Alex Bandziuk moveandinvest.com · office@moveandinvest.com
... A18: Если спросят про объём | B18: Прямо: сайт запущен в этом месяце, потока сегодня нет. Любая формулировка вроде «заявки идут» — неправда.

Sheet Легенда
A1: Как этим пользоваться
A3: Заполняешь ты | B3: Столбцы R–W: Статус, Дата отправки, Дата ответа, Что ответили про деньги, Заметки.
A4: Дата повтора | B4: Столбец T считается сам: дата отправки + 14 дней.
A5: Жёлтые строки | B5: День 1 — тринадцать писем: оба письма, оба типа адресатов, все четыре страны. Остальные 59 уходят следующим днём, если письма сработали.
A6: Голубая ячейка в «Модель» | B6: Письмо B: денег не просим, потому что закон не разрешает адресату их платить. Это не уступка, а единственная законная форма.
A7: Розовая ячейка | B7: У фирмы нет резидентства в практиках — «нет» вероятнее, и такой отказ ничего не говорит о письме.
A8: «Тип» | B8: Юрфирма или нет. Это главное деление в таблице: от него зависит, какое письмо уходит и можно ли вообще говорить о деньгах.
A9: Лицензии Мальты | B9: Коды RES-XXXX — из официального списка агентов Residency Malta (residencymalta.gov.mt/list-of-agents-residencymalta). Реестр читается напрямую; в документе от 1 сентября было сказано обратное — это исправление.
A10: Что список агентов НЕ доказывает | B10: Юридический статус. В том же списке KPMG, PwC, Deloitte, EY, Henley. Он доказывает только право подавать MPRP.
A11: Кого здесь нет | B11: Мультистрановые сравнительные площадки — Henley, Chetcuti Cauchi, Endevio, Discus, Latitude, Immigrant Invest, Dixcart, Sovereign, Global Citizen Solutions, Get Golden Visa, Atlas Consulting, Advisors Portugal, The Waypoint, Golden Port Visa, Acquest. Они конкурируют с нами за те же запросы: письмо им — бесплатная разведка нашей экономики. Плюс фирмы с неверными цифрами: EMD, Katsouris, GFDL, Al Tamimi, Al Kabban.
A12: Застройщиков нет | B12: На /about опубликовано, что проект не продаёт недвижимость и не берёт процент со сделки. Пока этот абзац стоит, застройщик партнёром быть не может. Это наше решение, а не норма.
A13: Кипра нет | B13: Гайда по стране нет — предлагать нечего.
A14: Языки | B14: Польского нет ни у кого, кроме офисного ящика WH Partners. Русский: Georgaki, Amoiridis, Awatif, Davidson & Co, возможно MoveTo.
... A17: Источник | B17: docs/partners-outreach-2026-09-01.md — кандидаты и обоснования; правки копий сайта от 1 сентября — /about, /enquiry, партнёрский блок, /for-partners.

Sheet Сводка
A1: Сводка
A3: Всего адресатов | B3: =COUNTA(Рассылка!D2:D73) -> 72
A4: В день 1 | B4: =COUNTIF(Рассылка!A2:A73,1) -> 13
A5: В день 2 | B5: =COUNTIF(Рассылка!A2:A73,2) -> 59
A6: Юрфирм | B6: =COUNTIF(Рассылка!C2:C73,"юрфирма") -> 32
A7: Не юрфирм | B7: =COUNTIF(Рассылка!C2:C73,"не юрфирма") -> 40
A8: Письмо A — про деньги | B8: =COUNTIF(Рассылка!M2:M73,"A") -> 47
A9: Письмо B — бесплатное | B9: =COUNTIF(Рассылка!M2:M73,"B") -> 25
A10: По email | B10: =COUNTIF(Рассылка!G2:G73,"email") -> 54
A11: Через форму | B11: =COUNTIF(Рассылка!G2:G73,"форма") -> 14
A12: Адрес не найден | B12: =COUNTIF(Рассылка!G2:G73,"не найден") -> 4
A13: Португалия | B13: =COUNTIF(Рассылка!B2:B73,"Португалия") -> 16
A14: Греция | B14: =COUNTIF(Рассылка!B2:B73,"Греция") -> 15
A15: Мальта | B15: =COUNTIF(Рассылка!B2:B73,"Мальта") -> 28
A16: ОАЭ | B16: =COUNTIF(Рассылка!B2:B73,"ОАЭ") -> 13
A17: Отправлено | B17: =COUNTIF(Рассылка!R2:R73,"отправлено") -> 0
A18: Ответ: да | B18: =COUNTIF(Рассылка!R2:R73,"ответ: да") -> 0
A19: Ответ: нет | B19: =COUNTIF(Рассылка!R2:R73,"ответ: нет") -> 0
A20: Нет ответа | B20: =COUNTIF(Рассылка!R2:R73,"нет ответа") -> 0
